eqfit/__init__.py
eqfit/model.py
eqfit-0.0.3.dist-info/LICENSE
eqfit-0.0.3.dist-info/METADATA
eqfit-0.0.3.dist-info/WHEEL
eqfit-0.0.3.dist-info/top_level.txt
eqfit-0.0.3.dist-info/RECORD
