Metadata-Version: 2.1
Name: eqfit
Version: 0.0.3
Summary: Equation fitting automation made simple with python
Home-page: https://github.com/SamPIngram/eqfit
Author: Sam Ingram
Author-email: sp_ingram12@yahoo.co.uk
License: UNKNOWN
Platform: UNKNOWN
Classifier: Programming Language :: Python :: 3
Classifier: License :: OSI Approved :: MIT License
Classifier: Operating System :: OS Independent
Requires-Python: >=3.5
Requires-Dist: numpy (>=1.19.2)
Requires-Dist: pandas (>=1.1.2)
Requires-Dist: matplotlib (>=3.3.1)
Requires-Dist: scikit-learn (>=0.23.2)
